expcomp/__init__.py
expcomp/condition.py
expcomp/evaluation/__init__.py
expcomp/evaluation/metric.py
expcomp/experiments/__init__.py
expcomp/experiments/experiment.py
expcomp/experiments/experiment_comparaisor.py
expcomp/experiments/experiment_config.py
expcomp/experiments/experiment_loader.py
expcomp-1.1.3.dist-info/METADATA
expcomp-1.1.3.dist-info/WHEEL
expcomp-1.1.3.dist-info/RECORD
