Metadata-Version: 2.3
Name: expcomp
Version: 1.1.3
Summary: 
Author: yassine rachidy
Author-email: ya.rachidy@gmail.com
Requires-Python: >=3.11
Classifier: Programming Language :: Python :: 3
Classifier: Programming Language :: Python :: 3.11
Classifier: Programming Language :: Python :: 3.12
Classifier: Programming Language :: Python :: 3.13
Requires-Dist: loguru (>=0.7.3,<0.8.0) ; python_version >= "3.11" and python_version < "4.0"
Requires-Dist: pandas (>=2.0.0)
Requires-Dist: pyaml (>=25.0.0)
